channels/__init__.py
channels/channel.py
channels/poller.py
channels/testing.py
yet_another_io_channels_library-0.2.4.post1.dist-info/LICENSE
yet_another_io_channels_library-0.2.4.post1.dist-info/METADATA
yet_another_io_channels_library-0.2.4.post1.dist-info/WHEEL
yet_another_io_channels_library-0.2.4.post1.dist-info/RECORD
