Metadata-Version: 2.1
Name: yet-another-io-channels-library
Version: 0.2.4.post1
Summary: Simple IO channels library
License: MIT
Author: Ilya Konovalov
Author-email: aragaer@gmail.com
Requires-Python: >=3.4,<4.0
Classifier: License :: OSI Approved :: MIT License
Classifier: Programming Language :: Python :: 3
Classifier: Programming Language :: Python :: 3.4
Classifier: Programming Language :: Python :: 3.5
Classifier: Programming Language :: Python :: 3.6
Classifier: Programming Language :: Python :: 3.7
Classifier: Programming Language :: Python :: 3.8
Classifier: Programming Language :: Python :: 3.9
Classifier: Programming Language :: Python :: 3.10
Classifier: Programming Language :: Python :: 3.11
Classifier: Programming Language :: Python :: 3.12
